{
"type": "FeatureCollection",
"name": "ppi_points",
"crs": { "type": "name", "properties": { "name": "urn:ogc:def:crs:OGC:1.3:CRS84" } },
"features": [
{ "type": "Feature", "properties": { "PPI_NOM": "Bouhertma 3", "PPI_GROUP": "BOUSSALEM BRAHMI BOUHERTMA", "PPI_GOV": "JENDOUBA", "Shape_Leng": 77707.886092300003, "Shape_Area": 69645142.608400002 }, "geometry": { "type": "Point", "coordinates": [ 8.996081374380255, 36.572811345279206 ] } },
{ "type": "Feature", "properties": { "PPI_NOM": "El Brahmi", "PPI_GROUP": "BOUSSALEM BRAHMI BOUHERTMA", "PPI_GOV": "JENDOUBA", "Shape_Leng": 47581.435255700002, "Shape_Area": 51653839.5933 }, "geometry": { "type": "Point", "coordinates": [ 8.885523285123432, 36.604881758474349 ] } }
]
}
